[
    {
        "data": "2024-12-11",
        "hora": "08:01:00",
        "temp. interior": 23.7,
        "temp. exterior": 26.1,
        "co2": 404.0,
        "ph": 4.04,
        "ce": 0.58
    },
    {
        "data": "2024-12-11",
        "hora": "08:11:00",
        "temp. interior": 23.9,
        "temp. exterior": 26.6,
        "co2": 408.0,
        "ph": 4.04,
        "ce": 0.57
    },
    {
        "data": "2024-12-11",
        "hora": "08:22:00",
        "temp. interior": 24.0,
        "temp. exterior": 27.3,
        "co2": 404.0,
        "ph": 4.08,
        "ce": 0.57
    },
    {
        "data": "2024-12-11",
        "hora": "08:32:00",
        "temp. interior": 24.4,
        "temp. exterior": 27.8,
        "co2": 399.0,
        "ph": 4.07,
        "ce": 0.56
    },
    {
        "data": "2024-12-11",
        "hora": "08:42:00",
        "temp. interior": 24.7,
        "temp. exterior": 28.7,
        "co2": 404.0,
        "ph": 4.04,
        "ce": 0.56
    },
    {
        "data": "2024-12-11",
        "hora": "08:52:00",
        "temp. interior": 25.1,
        "temp. exterior": 28.5,
        "co2": 404.0,
        "ph": 4.06,
        "ce": 0.56
    },
    {
        "data": "2024-12-11",
        "hora": "09:02:00",
        "temp. interior": 25.5,
        "temp. exterior": 29.2,
        "co2": 404.0,
        "ph": 4.02,
        "ce": 0.55
    },
    {
        "data": "2024-12-11",
        "hora": "09:12:00",
        "temp. interior": 25.8,
        "temp. exterior": 29.1,
        "co2": 399.0,
        "ph": 4.08,
        "ce": 0.54
    },
    {
        "data": "2024-12-11",
        "hora": "09:22:00",
        "temp. interior": 26.1,
        "temp. exterior": 29.5,
        "co2": 404.0,
        "ph": 4.06,
        "ce": 0.54
    },
    {
        "data": "2024-12-11",
        "hora": "09:32:00",
        "temp. interior": 26.4,
        "temp. exterior": 28.7,
        "co2": 404.0,
        "ph": 4.05,
        "ce": 0.54
    },
    {
        "data": "2024-12-11",
        "hora": "09:43:00",
        "temp. interior": 26.6,
        "temp. exterior": 29.4,
        "co2": 404.0,
        "ph": 4.04,
        "ce": 0.54
    },
    {
        "data": "2024-12-11",
        "hora": "09:53:00",
        "temp. interior": 26.8,
        "temp. exterior": 30.3,
        "co2": 404.0,
        "ph": 4.01,
        "ce": 0.53
    },
    {
        "data": "2024-12-11",
        "hora": "10:03:00",
        "temp. interior": 27.0,
        "temp. exterior": 30.6,
        "co2": 404.0,
        "ph": 4.04,
        "ce": 0.53
    },
    {
        "data": "2024-12-11",
        "hora": "10:13:00",
        "temp. interior": 27.3,
        "temp. exterior": 30.7,
        "co2": 404.0,
        "ph": 3.94,
        "ce": 0.54
    },
    {
        "data": "2024-12-11",
        "hora": "10:23:00",
        "temp. interior": 27.5,
        "temp. exterior": 31.6,
        "co2": 404.0,
        "ph": 4.02,
        "ce": 0.53
    },
    {
        "data": "2024-12-11",
        "hora": "10:33:00",
        "temp. interior": 27.7,
        "temp. exterior": 31.2,
        "co2": 399.0,
        "ph": 4.05,
        "ce": 0.53
    },
    {
        "data": "2024-12-11",
        "hora": "10:43:00",
        "temp. interior": 28.0,
        "temp. exterior": 30.9,
        "co2": 404.0,
        "ph": 4.13,
        "ce": 0.52
    },
    {
        "data": "2024-12-11",
        "hora": "10:53:00",
        "temp. interior": 28.3,
        "temp. exterior": 32.4,
        "co2": 404.0,
        "ph": 4.15,
        "ce": 0.53
    },
    {
        "data": "2024-12-11",
        "hora": "11:04:00",
        "temp. interior": 28.7,
        "temp. exterior": 33.2,
        "co2": 404.0,
        "ph": 4.05,
        "ce": 0.52
    },
    {
        "data": "2024-12-11",
        "hora": "11:14:00",
        "temp. interior": 29.1,
        "temp. exterior": 33.4,
        "co2": 396.0,
        "ph": 4.07,
        "ce": 0.51
    },
    {
        "data": "2024-12-11",
        "hora": "11:24:00",
        "temp. interior": 29.6,
        "temp. exterior": 35.1,
        "co2": 399.0,
        "ph": 4.02,
        "ce": 0.52
    },
    {
        "data": "2024-12-11",
        "hora": "11:34:00",
        "temp. interior": 30.0,
        "temp. exterior": 31.5,
        "co2": 399.0,
        "ph": 4.03,
        "ce": 0.51
    },
    {
        "data": "2024-12-11",
        "hora": "11:44:00",
        "temp. interior": 30.4,
        "temp. exterior": 31.9,
        "co2": 404.0,
        "ph": 3.87,
        "ce": 0.5
    },
    {
        "data": "2024-12-11",
        "hora": "11:54:00",
        "temp. interior": 30.8,
        "temp. exterior": 34.3,
        "co2": 399.0,
        "ph": 4.01,
        "ce": 0.5
    },
    {
        "data": "2024-12-11",
        "hora": "12:04:00",
        "temp. interior": 31.0,
        "temp. exterior": 33.8,
        "co2": 404.0,
        "ph": 3.97,
        "ce": 0.5
    },
    {
        "data": "2024-12-11",
        "hora": "12:14:00",
        "temp. interior": 31.3,
        "temp. exterior": 31.6,
        "co2": 399.0,
        "ph": 4.07,
        "ce": 0.5
    },
    {
        "data": "2024-12-11",
        "hora": "12:25:00",
        "temp. interior": 31.5,
        "temp. exterior": 34.4,
        "co2": 399.0,
        "ph": 4.02,
        "ce": 0.49
    },
    {
        "data": "2024-12-11",
        "hora": "12:35:00",
        "temp. interior": 31.7,
        "temp. exterior": 34.0,
        "co2": 404.0,
        "ph": 4.04,
        "ce": 0.5
    },
    {
        "data": "2024-12-11",
        "hora": "12:45:00",
        "temp. interior": 31.9,
        "temp. exterior": 34.1,
        "co2": 404.0,
        "ph": 4.08,
        "ce": 0.49
    },
    {
        "data": "2024-12-11",
        "hora": "12:55:00",
        "temp. interior": 32.0,
        "temp. exterior": 34.7,
        "co2": 404.0,
        "ph": 3.95,
        "ce": 0.5
    },
    {
        "data": "2024-12-11",
        "hora": "13:05:00",
        "temp. interior": 32.2,
        "temp. exterior": 33.4,
        "co2": 399.0,
        "ph": 4.09,
        "ce": 0.5
    },
    {
        "data": "2024-12-11",
        "hora": "13:15:00",
        "temp. interior": 32.5,
        "temp. exterior": 35.1,
        "co2": 399.0,
        "ph": 3.96,
        "ce": 0.5
    },
    {
        "data": "2024-12-11",
        "hora": "13:25:00",
        "temp. interior": 32.8,
        "temp. exterior": 35.2,
        "co2": 399.0,
        "ph": 4.07,
        "ce": 0.49
    },
    {
        "data": "2024-12-11",
        "hora": "13:36:00",
        "temp. interior": 33.1,
        "temp. exterior": 34.9,
        "co2": 399.0,
        "ph": 3.94,
        "ce": 0.49
    },
    {
        "data": "2024-12-11",
        "hora": "13:46:00",
        "temp. interior": 33.4,
        "temp. exterior": 34.4,
        "co2": 399.0,
        "ph": 4.06,
        "ce": 0.49
    },
    {
        "data": "2024-12-11",
        "hora": "13:56:00",
        "temp. interior": 33.6,
        "temp. exterior": 34.9,
        "co2": 404.0,
        "ph": 4.21,
        "ce": 0.48
    },
    {
        "data": "2024-12-11",
        "hora": "14:06:00",
        "temp. interior": 33.8,
        "temp. exterior": 34.4,
        "co2": 399.0,
        "ph": 4.11,
        "ce": 0.49
    },
    {
        "data": "2024-12-11",
        "hora": "14:16:00",
        "temp. interior": 33.9,
        "temp. exterior": 35.3,
        "co2": 399.0,
        "ph": 3.94,
        "ce": 0.48
    },
    {
        "data": "2024-12-11",
        "hora": "14:26:00",
        "temp. interior": 34.1,
        "temp. exterior": 35.3,
        "co2": 404.0,
        "ph": 4.05,
        "ce": 0.5
    },
    {
        "data": "2024-12-11",
        "hora": "14:36:00",
        "temp. interior": 34.2,
        "temp. exterior": 35.2,
        "co2": 404.0,
        "ph": 4.09,
        "ce": 0.48
    },
    {
        "data": "2024-12-11",
        "hora": "14:46:00",
        "temp. interior": 34.4,
        "temp. exterior": 35.1,
        "co2": 404.0,
        "ph": 3.93,
        "ce": 0.48
    },
    {
        "data": "2024-12-11",
        "hora": "14:57:00",
        "temp. interior": 34.5,
        "temp. exterior": 35.2,
        "co2": 404.0,
        "ph": 4.06,
        "ce": 0.48
    },
    {
        "data": "2024-12-11",
        "hora": "15:07:00",
        "temp. interior": 34.6,
        "temp. exterior": 35.7,
        "co2": 404.0,
        "ph": 3.97,
        "ce": 0.48
    },
    {
        "data": "2024-12-11",
        "hora": "15:17:00",
        "temp. interior": 34.8,
        "temp. exterior": 35.7,
        "co2": 408.0,
        "ph": 3.95,
        "ce": 0.48
    },
    {
        "data": "2024-12-11",
        "hora": "15:27:00",
        "temp. interior": 35.0,
        "temp. exterior": 35.1,
        "co2": 404.0,
        "ph": 3.99,
        "ce": 0.48
    },
    {
        "data": "2024-12-11",
        "hora": "15:37:00",
        "temp. interior": 35.2,
        "temp. exterior": 35.1,
        "co2": 408.0,
        "ph": 3.91,
        "ce": 0.47
    },
    {
        "data": "2024-12-11",
        "hora": "15:47:00",
        "temp. interior": 35.3,
        "temp. exterior": 34.7,
        "co2": 404.0,
        "ph": 4.09,
        "ce": 0.48
    },
    {
        "data": "2024-12-11",
        "hora": "15:57:00",
        "temp. interior": 35.4,
        "temp. exterior": 34.3,
        "co2": 404.0,
        "ph": 4.02,
        "ce": 0.48
    },
    {
        "data": "2024-12-11",
        "hora": "16:07:00",
        "temp. interior": 35.4,
        "temp. exterior": 34.6,
        "co2": 404.0,
        "ph": 4.17,
        "ce": 0.48
    },
    {
        "data": "2024-12-11",
        "hora": "16:18:00",
        "temp. interior": 35.3,
        "temp. exterior": 34.1,
        "co2": 404.0,
        "ph": 4.07,
        "ce": 0.48
    },
    {
        "data": "2024-12-11",
        "hora": "16:28:00",
        "temp. interior": 35.1,
        "temp. exterior": 34.6,
        "co2": 404.0,
        "ph": 4.1,
        "ce": 0.48
    },
    {
        "data": "2024-12-11",
        "hora": "16:38:00",
        "temp. interior": 34.8,
        "temp. exterior": 35.0,
        "co2": 404.0,
        "ph": 4.08,
        "ce": 0.49
    },
    {
        "data": "2024-12-11",
        "hora": "16:48:00",
        "temp. interior": 34.6,
        "temp. exterior": 35.2,
        "co2": 404.0,
        "ph": 4.1,
        "ce": 0.49
    },
    {
        "data": "2024-12-11",
        "hora": "16:58:00",
        "temp. interior": 34.3,
        "temp. exterior": 34.8,
        "co2": 404.0,
        "ph": 4.05,
        "ce": 0.5
    },
    {
        "data": "2024-12-11",
        "hora": "17:08:00",
        "temp. interior": 34.1,
        "temp. exterior": 33.8,
        "co2": 408.0,
        "ph": 4.12,
        "ce": 0.5
    },
    {
        "data": "2024-12-11",
        "hora": "17:18:00",
        "temp. interior": 34.0,
        "temp. exterior": 34.5,
        "co2": 404.0,
        "ph": 4.02,
        "ce": 0.5
    },
    {
        "data": "2024-12-11",
        "hora": "17:28:00",
        "temp. interior": 33.9,
        "temp. exterior": 34.6,
        "co2": 404.0,
        "ph": 4.07,
        "ce": 0.5
    },
    {
        "data": "2024-12-11",
        "hora": "17:39:00",
        "temp. interior": 33.8,
        "temp. exterior": 34.7,
        "co2": 404.0,
        "ph": 4.07,
        "ce": 0.51
    },
    {
        "data": "2024-12-11",
        "hora": "17:49:00",
        "temp. interior": 33.6,
        "temp. exterior": 34.7,
        "co2": 404.0,
        "ph": 4.1,
        "ce": 0.5
    },
    {
        "data": "2024-12-11",
        "hora": "17:59:00",
        "temp. interior": 33.5,
        "temp. exterior": 34.4,
        "co2": 404.0,
        "ph": 4.03,
        "ce": 0.5
    },
    {
        "data": "2024-12-11",
        "hora": "18:09:00",
        "temp. interior": 33.4,
        "temp. exterior": 34.1,
        "co2": 408.0,
        "ph": 4.09,
        "ce": 0.51
    },
    {
        "data": "2024-12-11",
        "hora": "18:19:00",
        "temp. interior": 33.3,
        "temp. exterior": 33.5,
        "co2": 404.0,
        "ph": 4.07,
        "ce": 0.51
    },
    {
        "data": "2024-12-11",
        "hora": "18:29:00",
        "temp. interior": 33.2,
        "temp. exterior": 33.6,
        "co2": 404.0,
        "ph": 4.07,
        "ce": 0.51
    },
    {
        "data": "2024-12-11",
        "hora": "18:39:00",
        "temp. interior": 33.0,
        "temp. exterior": 33.3,
        "co2": 404.0,
        "ph": 4.08,
        "ce": 0.52
    },
    {
        "data": "2024-12-11",
        "hora": "18:49:00",
        "temp. interior": 32.8,
        "temp. exterior": 32.4,
        "co2": 399.0,
        "ph": 4.1,
        "ce": 0.51
    },
    {
        "data": "2024-12-11",
        "hora": "19:00:00",
        "temp. interior": 32.5,
        "temp. exterior": 31.8,
        "co2": 399.0,
        "ph": 4.07,
        "ce": 0.52
    },
    {
        "data": "2024-12-11",
        "hora": "19:10:00",
        "temp. interior": 32.2,
        "temp. exterior": 30.6,
        "co2": 404.0,
        "ph": 3.99,
        "ce": 0.52
    },
    {
        "data": "2024-12-11",
        "hora": "19:20:00",
        "temp. interior": 31.7,
        "temp. exterior": 29.5,
        "co2": 399.0,
        "ph": 4.06,
        "ce": 0.52
    },
    {
        "data": "2024-12-11",
        "hora": "19:30:00",
        "temp. interior": 31.3,
        "temp. exterior": 28.3,
        "co2": 399.0,
        "ph": 4.05,
        "ce": 0.53
    },
    {
        "data": "2024-12-11",
        "hora": "19:40:00",
        "temp. interior": 30.8,
        "temp. exterior": 28.1,
        "co2": 399.0,
        "ph": 4.02,
        "ce": 0.54
    },
    {
        "data": "2024-12-11",
        "hora": "19:50:00",
        "temp. interior": 30.2,
        "temp. exterior": 27.0,
        "co2": 399.0,
        "ph": 4.14,
        "ce": 0.54
    }
]